BarcodeFinder/__init__.py
BarcodeFinder/__main__.py
BarcodeFinder/bf.py
BarcodeFinder/evaluate.py
BarcodeFinder/gb2fasta.py
BarcodeFinder/global_vars.py
BarcodeFinder/primer.py
BarcodeFinder/utils.py
BarcodeFinder/cli/__init__.py
BarcodeFinder/data/animal_orders.csv
BarcodeFinder/data/classes.csv
BarcodeFinder/data/kingdoms.csv
BarcodeFinder/data/phyla.csv
BarcodeFinder/data/superkingdoms.csv
BarcodeFinder-0.9.49.dist-info/LICENSE
BarcodeFinder-0.9.49.dist-info/METADATA
BarcodeFinder-0.9.49.dist-info/WHEEL
BarcodeFinder-0.9.49.dist-info/top_level.txt
BarcodeFinder-0.9.49.dist-info/RECORD
