Metadata-Version: 2.1
Name: BarcodeFinder
Version: 0.9.49
Summary: All-in-one solution for discovering novel DNA barcode
Home-page: https://github.com/wpwupingwp/BarcodeFinder
Author: Ping Wu
Author-email: wpwupingwp@outlook.com
License: GNU AGPL v3
Platform: UNKNOWN
Classifier: Development Status :: 4 - Beta
Classifier: Intended Audience :: Developers
Classifier: Intended Audience :: Science/Research
Classifier: License :: OSI Approved :: GNU Affero General Public License v3
Classifier: Operating System :: OS Independent
Classifier: Programming Language :: Python :: 3.5
Classifier: Programming Language :: Python :: 3.6
Classifier: Programming Language :: Python :: 3.7
Classifier: Topic :: Scientific/Engineering :: Bio-Informatics
Requires-Dist: biopython (>=1.72)
Requires-Dist: certifi (>=2018.11.29)
Requires-Dist: coloredlogs (>=10.0)
Requires-Dist: matplotlib (>=3.0.0)
Requires-Dist: numpy (>=1.15.2)
Requires-Dist: pip (>=18.0)
Requires-Dist: primer3-py (>=0.6.0)
Requires-Dist: wheel (>=0.32.3)
